tecana/__init__.py
tecana/core.py
tecana-1.1.0.dist-info/licenses/LICENSE
tecana-1.1.0.dist-info/METADATA
tecana-1.1.0.dist-info/WHEEL
tecana-1.1.0.dist-info/top_level.txt
tecana-1.1.0.dist-info/RECORD
